run_server.py
a2a_server/__init__.py
a2a_server/a2a_agent_card.py
a2a_server/a2a_errors.py
a2a_server/a2a_executor.py
a2a_server/a2a_router.py
a2a_server/a2a_types.py
a2a_server/admin_api.py
a2a_server/agent_card.py
a2a_server/agents_server.py
a2a_server/auth_api.py
a2a_server/automation_api.py
a2a_server/billing_api.py
a2a_server/billing_service.py
a2a_server/billing_webhooks.py
a2a_server/config.py
a2a_server/database.py
a2a_server/email_api.py
a2a_server/email_inbound.py
a2a_server/email_notifications.py
a2a_server/enhanced_agents.py
a2a_server/enhanced_server.py
a2a_server/hosted_worker.py
a2a_server/integrated_agents_server.py
a2a_server/k8s_provisioning.py
a2a_server/keycloak_auth.py
a2a_server/livekit_bridge.py
a2a_server/marketing_tools.py
a2a_server/mcp_client.py
a2a_server/mcp_http_server.py
a2a_server/mcp_server.py
a2a_server/message_broker.py
a2a_server/mock_mcp.py
a2a_server/model_resolver.py
a2a_server/models.py
a2a_server/monitor_api.py
a2a_server/opencode_bridge.py
a2a_server/provisioning_service.py
a2a_server/queue_api.py
a2a_server/redis_task_manager.py
a2a_server/rls.py
a2a_server/server.py
a2a_server/task_manager.py
a2a_server/task_queue.py
a2a_server/task_reaper.py
a2a_server/tenant_api.py
a2a_server/tenant_middleware.py
a2a_server/tenant_service.py
a2a_server/user_auth.py
a2a_server/user_billing.py
a2a_server/vault_client.py
a2a_server/webhook_security.py
a2a_server/worker_sse.py
agent_worker/__init__.py
agent_worker/worker.py
codetether/__init__.py
codetether/__main__.py
codetether/cli.py
codetether/worker_cli.py
codetether-1.4.3.dist-info/licenses/LICENSE
codetether_voice_agent/__init__.py
codetether_voice_agent/agent.py
codetether_voice_agent/codetether_mcp.py
codetether_voice_agent/config.py
codetether_voice_agent/functiongemma_caller.py
codetether_voice_agent/session_playback.py
codetether_voice_agent/tools/__init__.py
codetether_voice_agent/tools/definitions.py
codetether_voice_agent/tools/handlers.py
ui/monitor-tailwind.html
ui/monitor.html
ui/monitor.js
codetether-1.4.3.dist-info/METADATA
codetether-1.4.3.dist-info/WHEEL
codetether-1.4.3.dist-info/entry_points.txt
codetether-1.4.3.dist-info/top_level.txt
codetether-1.4.3.dist-info/RECORD
