Metadata-Version: 2.4
Name: codetether
Version: 1.4.3
Summary: CodeTether: A2A Protocol v0.3 compliant agent orchestration platform with MCP + OpenCode integration
Home-page: https://github.com/rileyseaburg/codetether
Author: CodeTether Contributors
Author-email: 
Classifier: Development Status :: 4 - Beta
Classifier: Intended Audience :: Developers
Classifier: License :: OSI Approved :: MIT License
Classifier: Programming Language :: Python :: 3
Classifier: Programming Language :: Python :: 3.10
Classifier: Programming Language :: Python :: 3.11
Classifier: Programming Language :: Python :: 3.12
Requires-Python: >=3.10
License-File: LICENSE
Requires-Dist: fastapi>=0.104.0
Requires-Dist: uvicorn>=0.24.0
Requires-Dist: pydantic>=2.0.0
Requires-Dist: httpx>=0.25.0
Requires-Dist: aiohttp>=3.9.0
Requires-Dist: redis>=5.0.0
Requires-Dist: mcp>=1.0.0
Requires-Dist: livekit>=0.15.0
Requires-Dist: livekit-api>=1.0.0
Requires-Dist: a2a-sdk[http-server]>=0.3.22
Provides-Extra: test
Requires-Dist: pytest>=7.4.0; extra == "test"
Requires-Dist: pytest-asyncio>=0.21.0; extra == "test"
Requires-Dist: pytest-cov>=4.1.0; extra == "test"
Provides-Extra: dev
Requires-Dist: black>=23.0.0; extra == "dev"
Requires-Dist: ruff>=0.1.0; extra == "dev"
Requires-Dist: mypy>=1.6.0; extra == "dev"
Dynamic: author
Dynamic: classifier
Dynamic: description
Dynamic: description-content-type
Dynamic: home-page
Dynamic: license-file
Dynamic: provides-extra
Dynamic: requires-dist
Dynamic: requires-python
Dynamic: summary
